otpyf/__init__.py
otpyf/otpyf.py
otpyf-1.0.0.dist-info/LICENSE
otpyf-1.0.0.dist-info/METADATA
otpyf-1.0.0.dist-info/WHEEL
otpyf-1.0.0.dist-info/top_level.txt
otpyf-1.0.0.dist-info/RECORD
